githubcap/__init__.py
githubcap/base.py
githubcap/cli.py
githubcap/configuration.py
githubcap/enums.py
githubcap/exceptions.py
githubcap/utils.py
githubcap/resources/__init__.py
githubcap/resources/issue.py
githubcap/resources/issues.py
githubcap/resources/label.py
githubcap/resources/milestone.py
githubcap/resources/user.py
githubcap/schemas/__init__.py
githubcap/schemas/issue.py
githubcap/schemas/label.py
githubcap/schemas/milestone.py
githubcap/schemas/user.py
githubcap/test/__init__.py
githubcap-0.0.0.dist-info/DESCRIPTION.rst
githubcap-0.0.0.dist-info/METADATA
githubcap-0.0.0.dist-info/RECORD
githubcap-0.0.0.dist-info/WHEEL
githubcap-0.0.0.dist-info/entry_points.txt
githubcap-0.0.0.dist-info/metadata.json
githubcap-0.0.0.dist-info/top_level.txt
