Metadata-Version: 1.1
Name: githubcap
Version: 0.0.0
Summary: Tool and library for interacting with GitHub API v3
Home-page: https://github.com/fridex/githubcap
Author: Fridolin Pokorny
Author-email: fridolin.pokorny@gmail.com
License: ASL v2.0
Keywords: github tool api
Platform: UNKNOWN
Classifier: Development Status :: 4 - Beta
Classifier: Programming Language :: Python :: 3
Classifier: Programming Language :: Python :: 3.4
Classifier: Programming Language :: Python :: 3.5
Classifier: Environment :: Console
Classifier: Intended Audience :: Developers
Classifier: License :: OSI Approved :: Apache Software License
Classifier: Operating System :: OS Independent
Classifier: Programming Language :: Python :: Implementation :: CPython
Classifier: Programming Language :: Python :: Implementation :: PyPy
